Urna.v
module Urna(Valid, Digit, Finish, Clock, C1, C2, C3, C4, Nulo, VoteStatus);
  input wire [3:0]Digit;
  input wire Valid, Finish, Clock;
  output reg VoteStatus;
  output reg [7:0]C1;
  output reg [7:0]C2;
  output reg [7:0]C3;
  output reg [7:0]C4;
  output reg [7:0]Nulo;
  always @(posedge Clock) begin
      if(Finish) begin
          C1 <= 8'b00000000;
          C2 <= 8'b00000000;
          C3 <= 8'b00000000;
          C4 <= 8'b00000000;
          Nulo <= 8'b00000000;
      end
      if(~Finish) begin
        if((Digit[3]==0)&(Digit[2]==0)&(Digit[1]==0)&(Digit[0]==1)&(Valid)) begin
            VoteStatus <= 1;
            C1 <= C1 + 8'b00000001;
        end
        else if((Digit[3]==0)&(Digit[2]==1)&(Digit[1]==0)&(Digit[0]==1)&(Valid)) begin
            VoteStatus <= 1;
            C2 <= C2 + 8'b00000001;
        end
        else if((Digit[3]==0)&(Digit[2]==1)&(Digit[1]==1)&(Digit[0]==0)&(Valid)) begin
            VoteStatus <= 1;
            C3 <= C3 + 8'b00000001;
        end
        else if((Digit[3]==1)&(Digit[2]==0)&(Digit[1]==0)&(Digit[0]==0)&(Valid)) begin
            VoteStatus <= 1;
            C4 <= C4 + 8'b00000001;
        end
        else begin
            VoteStatus <= 0;
            Nulo <= Nulo + 8'b00000001;
        end
      end
  end
endmodule

testbench.v
`include "Urna.v"
module testbench();
  reg [3:0]Digit;
  reg Valid, Finish, Clock;
  wire VoteStatus;
  wire [7:0]C1;
  wire [7:0]C2;
  wire [7:0]C3;
  wire [7:0]C4;
  wire [7:0]Nulo;
  Urna moduloUrna(.Valid(Valid), .Digit(Digit), .Finish(Finish), .Clock(Clock), .C1(C1), .C2(C2), .C3(C3), .C4(C4), .Nulo(Nulo), .VoteStatus(VoteStatus));
  initial begin
    $dumpfile("Urna.vcd");
    $dumpvars(0, testbench);
    $display("Exibindo a eleicao:");
    $monitor("C1: %b\nC2: %b\nC3: %b\nC4: %b\nNulo: %b\n", C1, C2, C3, C4, Nulo);
  end
  initial begin
    #1; Clock = 0;
    #1; Clock = 1; Finish = 1;
    #1; Clock = 0;
    #1; Clock = 1; Finish = 0; Digit = 4'b0001; Valid = 1;
    #1; Clock = 0;
    #1; Clock = 1; Finish = 0; Digit = 4'b0101; Valid = 1;
    #1; Clock = 0;
    #1; Clock = 1; Finish = 0; Digit = 4'b0110; Valid = 1;
    #1; Clock = 0;
    #1; Clock = 1; Finish = 0; Digit = 4'b1000; Valid = 1;
    #1; Clock = 0;
    #1; Clock = 1; Finish = 0; Digit = 4'b1010; Valid = 1;
    #1; Clock = 0;
    #1; Clock = 1; Finish = 1;
    #1;
  end
endmodule

Urna.vcd
$date
	Tue Nov 20 10:06:55 2018
$end
$version
	Icarus Verilog
$end
$timescale
	1s
$end
$scope module testbench $end
$var wire 1 ! VoteStatus $end
$var wire 8 " Nulo [7:0] $end
$var wire 8 # C4 [7:0] $end
$var wire 8 $ C3 [7:0] $end
$var wire 8 % C2 [7:0] $end
$var wire 8 & C1 [7:0] $end
$var reg 1 ' Clock $end
$var reg 4 ( Digit [3:0] $end
$var reg 1 ) Finish $end
$var reg 1 * Valid $end
$scope module moduloUrna $end
$var wire 1 ' Clock $end
$var wire 4 + Digit [3:0] $end
$var wire 1 ) Finish $end
$var wire 1 * Valid $end
$var reg 8 , C1 [7:0] $end
$var reg 8 - C2 [7:0] $end
$var reg 8 . C3 [7:0] $end
$var reg 8 / C4 [7:0] $end
$var reg 8 0 Nulo [7:0] $end
$var reg 1 ! VoteStatus $end
$upscope $end
$upscope $end
$enddefinitions $end
#0
$dumpvars
bx 0
bx /
bx .
bx -
bx ,
bx +
x*
x)
bx (
x'
bx &
bx %
bx $
bx #
bx "
x!
$end
#1
0'
#2
b0 "
b0 0
b0 #
b0 /
b0 $
b0 .
b0 %
b0 -
b0 &
b0 ,
1)
1'
#3
0'
#4
b1 &
b1 ,
1!
1*
b1 (
b1 +
0)
1'
#5
0'
#6
b1 %
b1 -
b101 (
b101 +
1'
#7
0'
#8
b1 $
b1 .
b110 (
b110 +
1'
#9
0'
#10
b1 #
b1 /
b1000 (
b1000 +
1'
#11
0'
#12
b1 "
b1 0
0!
b1010 (
b1010 +
1'
#13
0'
#14
b0 "
b0 0
b0 #
b0 /
b0 $
b0 .
b0 %
b0 -
b0 &
b0 ,
1)
1'
